MilOcr.py
MilOcr-1.0.dist-info/METADATA
MilOcr-1.0.dist-info/WHEEL
MilOcr-1.0.dist-info/top_level.txt
MilOcr-1.0.dist-info/RECORD
