Metadata-Version: 2.1
Name: MilOcr
Version: 1.0
Requires-Dist: craft-text-detector ==0.4.3
Requires-Dist: cycler ==0.12.1
Requires-Dist: filelock ==3.13.1
Requires-Dist: fonttools ==4.49.0
Requires-Dist: fsspec ==2024.2.0
Requires-Dist: gdown ==5.1.0
Requires-Dist: idna ==3.6
Requires-Dist: importlib-resources ==6.3.0
Requires-Dist: jinja2 ==3.1.3
Requires-Dist: kiwisolver ==1.4.5
Requires-Dist: markupsafe ==2.1.5
Requires-Dist: matplotlib ==3.7.5
Requires-Dist: mpmath ==1.3.0
Requires-Dist: networkx ==3.1
Requires-Dist: numpy ==1.21.6
Requires-Dist: opencv-python ==4.5.4.60
Requires-Dist: packaging ==24.0
Requires-Dist: pandas ==2.0.3
Requires-Dist: pillow
Requires-Dist: pyparsing ==3.1.2
Requires-Dist: pysocks ==1.7.1
Requires-Dist: pytesseract ==0.3.10
Requires-Dist: python-dateutil ==2.9.0.post0
Requires-Dist: pytz ==2024.1
Requires-Dist: requests ==2.31.0
Requires-Dist: scipy ==1.10.1
Requires-Dist: setuptools ==68.2.2
Requires-Dist: six ==1.16.0
Requires-Dist: soupsieve ==2.5
Requires-Dist: typing-extensions ==4.10.0
Requires-Dist: tzdata ==2024.1
Requires-Dist: urllib3 ==2.2.1
Requires-Dist: wheel ==0.41.2
Requires-Dist: zipp ==3.18.0
